Metadata-Version: 2.1
Name: scientific-paper-matplotlib
Version: 0.0.3
Summary: This package is for publishers who wants a ready_use plot configuration like label size and datetime config... etc
Home-page: UNKNOWN
Author: Khaled Alamin
Author-email: khaled.alamin@gmail.com
License: UNKNOWN
Platform: UNKNOWN
Classifier: Programming Language :: Python :: 3
Classifier: License :: OSI Approved :: MIT License
Classifier: Operating System :: OS Independent
Requires-Python: >=3.6
